auto_tests/__init__.py
auto_tests/auto_tests.py
auto_tests/formats.py
auto_tests-0.1.dist-info/METADATA
auto_tests-0.1.dist-info/WHEEL
auto_tests-0.1.dist-info/top_level.txt
auto_tests-0.1.dist-info/RECORD
