Metadata-Version: 2.1
Name: auto-tests
Version: 0.1
Summary: package for fast testing console code
Home-page: https://github.com/pavelglazunov/-LIB-autoTests
License: UNKNOWN
Platform: UNKNOWN
